ez_setup.py
setup.py
wsgiview/__init__.py
wsgiview.egg-info/PKG-INFO
wsgiview.egg-info/SOURCES.txt
wsgiview.egg-info/dependency_links.txt
wsgiview.egg-info/requires.txt
wsgiview.egg-info/top_level.txt
wsgiview.egg-info/zip-safe
