Metadata-Version: 1.0
Name: wsgiview
Version: 0.2.1
Summary: Use Any TurboGears Template Plug-in Anywhere.
Home-page: UNKNOWN
Author: L. C. Rees
Author-email: lcrees@gmail.com
License: UNKNOWN
Keywords: template TurboGears Buffet plug-in WSGI
Platform: UNKNOWN
Classifier: Development Status :: 4 - Beta
Classifier: Framework :: TurboGears
Classifier: Environment :: Web Environment
Classifier: License :: OSI Approved :: BSD License
Classifier: Natural Language :: English
Classifier: Operating System :: OS Independent
Classifier: Programming Language :: Python
Classifier: Topic :: Internet :: WWW/HTTP :: Dynamic Content
Classifier: Topic :: Text Processing :: Markup :: HTML
Classifier: Topic :: Text Processing :: Markup :: XML
Classifier: Topic :: Internet :: WWW/HTTP :: WSGI :: Middleware
